TCKN_generator/__init__.py
TCKN_generator/generator.py
TCKN_generator/validator.py
TCKN_generator-0.0.1.dist-info/LICENSE
TCKN_generator-0.0.1.dist-info/METADATA
TCKN_generator-0.0.1.dist-info/WHEEL
TCKN_generator-0.0.1.dist-info/top_level.txt
TCKN_generator-0.0.1.dist-info/RECORD
