Metadata-Version: 2.1
Name: TCKN-generator
Version: 0.0.1
Summary: Turkish citizen idendity number generator and validator python package for test purposes only
Author-email: Kadir Kaya <kadir.kaya2859@gmail.com>, Cuneyd Kaya <cgultekink@gmail.com>
Project-URL: Homepage, https://github.com/Catch-XXII/TCKN_Generator
Project-URL: Bug Tracker, https://github.com/Catch-XXII/TCKN_Generator/issues
Classifier: Programming Language :: Python :: 3
Classifier: License :: OSI Approved :: MIT License
Classifier: Operating System :: OS Independent
Requires-Python: >=3.7
License-File: LICENSE
